prototype_python_library/__init__.py
prototype_python_library-0.13.0.dist-info/METADATA
prototype_python_library-0.13.0.dist-info/WHEEL
prototype_python_library-0.13.0.dist-info/LICENSE
prototype_python_library-0.13.0.dist-info/RECORD
