Metadata-Version: 2.1
Name: prototype-python-library
Version: 0.13.0
Summary: A prototype python library.
Home-page: https://github.com/91nunocosta/prototype-python-library/
License: MIT
Author: Nuno Costa
Author-email: 91nunocosta@gmail.com
Requires-Python: >=3.8,<4.0
Classifier: License :: OSI Approved :: MIT License
Classifier: Programming Language :: Python :: 3
Classifier: Programming Language :: Python :: 3.8
Classifier: Programming Language :: Python :: 3.9
Classifier: Programming Language :: Python :: 3.10
Classifier: Programming Language :: Python :: 3.11
Project-URL: Documentation, https://91nunocosta.github.io/prototype-python-library/prototype_python_library.html
Project-URL: Repository, https://github.com/91nunocosta/prototype-python-library/
